{"updated":"2026-07-21T06:45:09.945082+00:00","items":[{"title":"早报｜二季度华为手机份额升至23%/广汽本田与本田续签合资协议至2038年/《复仇者联盟5》首曝预告","link":"https://www.ifanr.com/1672637?utm_source=rss&utm_medium=rss&utm_campaign=","description":"· 靳玉志：华为乾崑继续做汽车行业的「电子螺丝钉」\n· 工信部：我国智能算力规模达到 2185 EFLOPS\n· 字节跳动发布 Seed Audio 1.0 音频创作模型#欢迎关注爱范儿官方微信公众号：爱范儿（微信号：ifanr），更多精彩内容第一时间为您奉上。","pubDate":"2026-07-21T00:54:22+00:00","source":"爱范儿","color":"#3fb950"},{"title":"GMI Cloud  “无界造物节”在WAIC圆满完赛，“MaaS+创意”赋能 AI 创作新生态！","link":"https://www.qbitai.com/2026/07/455593.html","description":"GMI Cloud × HappyHorse 共建 AI 创作生态","pubDate":"2026-07-20T08:52:26+00:00","source":"量子位","color":"#bc8cff"},{"title":"具透 | watchOS 27 公测版一览：动态应用网格、Liquid Glass 微调……","link":"https://sspai.com/post/112430","description":"AI 之外，watchOS 27 中还有这些新功能。查看全文","pubDate":"2026-07-17T15:00:00+08:00","source":"少数派","color":"#8b949e"}]}